coilpy-0.4.3.dist-info/METADATA
coilpy-0.4.3.dist-info/WHEEL
coilpy_fortranmodule.c
coilpy_fortran.cp313-win_amd64.pyd
coilpy_fortran.cp313-win_amd64.dll.a
coilpy/booz_xform.py
coilpy/coils.py
coilpy/current_potential.py
coilpy/dipole.py
coilpy/focushdf5.py
coilpy/hdf5.py
coilpy/__init__.py
coilpy/magnet.py
coilpy/magtense_interface.py
coilpy/mgrid.py
coilpy/misc.py
coilpy/netcdf.py
coilpy/pm4stell.py
coilpy/sortedDict.py
coilpy/stellopt.py
coilpy/surface.py
coilpy/vmec.py
coilpy-0.4.3.dist-info/RECORD
