Metadata-Version: 2.1
Name: coilpy
Version: 0.4.3
Summary: Plotting and data processing tools for plasma and coil
Author-Email: Caoxiang Zhu <caoxiangzhu@gmail.com>
Maintainer-Email: Caoxiang Zhu <caoxiangzhu@gmail.com>
License: GNU 3.0
Classifier: Development Status :: 3 - Alpha
Classifier: License :: OSI Approved :: GNU Lesser General Public License v3 or later (LGPLv3+)
Classifier: Programming Language :: Python :: 3
Classifier: Topic :: Scientific/Engineering
Requires-Dist: scipy
Requires-Dist: xarray
Requires-Dist: h5py
Requires-Dist: matplotlib
Requires-Dist: pandas
Requires-Dist: plotly
Requires-Dist: numpy
Requires-Dist: pyevtk
Requires-Dist: classes
Requires-Dist: f90nml
Requires-Dist: meshio
